anyenv/__init__.py
anyenv/anypath.py
anyenv/as_generated.py
anyenv/async_run.py
anyenv/calling/__init__.py
anyenv/calling/async_executor.py
anyenv/calling/multieventhandler.py
anyenv/calling/threadgroup.py
anyenv/download/__init__.py
anyenv/download/aiohttp_backend/__init__.py
anyenv/download/aiohttp_backend/backend.py
anyenv/download/base.py
anyenv/download/exceptions.py
anyenv/download/functional.py
anyenv/download/http_types.py
anyenv/download/httpx_backend/__init__.py
anyenv/download/httpx_backend/backend.py
anyenv/download/httpx_backend/js_transport.py
anyenv/download/middleware.py
anyenv/download/pyodide_backend/__init__.py
anyenv/download/pyodide_backend/backend.py
anyenv/helpers.py
anyenv/json_tools/__init__.py
anyenv/json_tools/base.py
anyenv/json_tools/msgspec_provider/__init__.py
anyenv/json_tools/msgspec_provider/provider.py
anyenv/json_tools/orjson_provider/__init__.py
anyenv/json_tools/orjson_provider/provider.py
anyenv/json_tools/pydantic_provider/__init__.py
anyenv/json_tools/pydantic_provider/provider.py
anyenv/json_tools/stdlib_provider/__init__.py
anyenv/json_tools/stdlib_provider/provider.py
anyenv/json_tools/utils.py
anyenv/language_formatters/__init__.py
anyenv/language_formatters/_base.py
anyenv/language_formatters/_elixir.py
anyenv/language_formatters/_jvm.py
anyenv/language_formatters/_python.py
anyenv/language_formatters/_r.py
anyenv/language_formatters/_registry.py
anyenv/language_formatters/_ruby.py
anyenv/language_formatters/_systems.py
anyenv/language_formatters/_toml.py
anyenv/language_formatters/_web.py
anyenv/log.py
anyenv/lsp_servers/__init__.py
anyenv/lsp_servers/_base.py
anyenv/lsp_servers/_registry.py
anyenv/lsp_servers/_runner.py
anyenv/lsp_servers/_servers/__init__.py
anyenv/lsp_servers/_servers/c_lsps.py
anyenv/lsp_servers/_servers/c_sharp_lsps.py
anyenv/lsp_servers/_servers/dart_lsps.py
anyenv/lsp_servers/_servers/elixir_lsps.py
anyenv/lsp_servers/_servers/go_lsps.py
anyenv/lsp_servers/_servers/java_lsps.py
anyenv-2.0.12.dist-info/licenses/LICENSE
anyenv-2.0.12.dist-info/WHEEL
anyenv-2.0.12.dist-info/METADATA
anyenv-2.0.12.dist-info/RECORD
