Metadata-Version: 2.4
Name: anyenv
Version: 2.0.12
Summary: Compatibility layer for some basic operations to allow painless operation in PyOdide and Python pre-releases
Keywords: 
Author: Philipp Temminghoff
Author-email: Philipp Temminghoff <philipptemminghoff@googlemail.com>
License-Expression: MIT
License-File: LICENSE
Classifier: Development Status :: 4 - Beta
Classifier: Intended Audience :: Developers
Classifier: Operating System :: OS Independent
Classifier: Programming Language :: Python :: 3
Classifier: Programming Language :: Python :: 3 :: Only
Classifier: Programming Language :: Python :: 3.12
Classifier: Programming Language :: Python :: 3.13
Classifier: Programming Language :: Python :: 3.14
Classifier: Topic :: Documentation
Classifier: Topic :: Software Development
Classifier: Topic :: Utilities
Classifier: Typing :: Typed
Requires-Dist: aioitertools>=0.12.0
Requires-Dist: anyio>=4.8.0
Requires-Dist: appdirs>=1.4.4
Requires-Dist: universal-pathlib>=0.3.4
Requires-Dist: aiohttp ; extra == 'aiohttp'
Requires-Dist: aiohttp-client-cache ; extra == 'aiohttp'
Requires-Dist: exxec>=0.1.1 ; extra == 'exxec'
Requires-Dist: httpx ; extra == 'httpx'
Requires-Dist: hishel[async]>=1.0.0 ; extra == 'httpx'
Requires-Dist: msgspec ; extra == 'msgspec'
Requires-Dist: pytomlpp ; python_full_version < '3.14' and extra == 'pytomlpp'
Requires-Dist: rtoml ; extra == 'rtoml'
Requires-Dist: toml-rs ; extra == 'toml-rs'
Requires-Python: >=3.13
Project-URL: Code coverage, https://app.codecov.io/gh/phil65/anyenv
Project-URL: Discussions, https://github.com/phil65/anyenv/discussions
Project-URL: Documentation, https://phil65.github.io/anyenv/
Project-URL: Issues, https://github.com/phil65/anyenv/issues
Project-URL: Source, https://github.com/phil65/anyenv
Provides-Extra: aiohttp
Provides-Extra: exxec
Provides-Extra: httpx
Provides-Extra: msgspec
Provides-Extra: pytomlpp
Provides-Extra: rtoml
Provides-Extra: toml-rs
